[
  {
    "name": "24hMoney",
    "url": "https://24hmoney.vn/rss/chung-khoan.rss"
  },
  {
    "name": "VnEconomy",
    "url": "https://vneconomy.vn/thi-truong-chung-khoan.rss"
  },
  {
    "name": "Vietstock",
    "url": "https://vietstock.vn/144/chung-khoan.rss"
  },
  {
    "name": "VnExpress Kinh doanh",
    "url": "https://vnexpress.net/rss/kinh-doanh.rss"
  },
  {
    "name": "Dân Trí Kinh doanh",
    "url": "https://dantri.com.vn/rss/kinh-doanh.rss"
  },
  {
    "name": "MarketTimes Chứng khoán",
    "url": "https://markettimes.vn/rss/chung-khoan.rss"
  },
  {
    "name": "BBC Business",
    "url": "https://feeds.bbci.co.uk/news/business/rss.xml"
  },
  {
    "name": "WSJ Markets",
    "url": "https://feeds.a.dj.com/rss/RSSMarketsMain.xml"
  },
  {
    "name": "Yahoo Finance",
    "url": "https://finance.yahoo.com/news/rssindex"
  },
  {
    "name": "Thanh Niên Chứng khoán",
    "url": "https://thanhnien.vn/rss/kinh-te/chung-khoan.rss"
  }
]